doepy3/__init__.py
doepy3/build.py
doepy3/doe_functions.py
doepy3/pydoe_corrected.py
doepy3/read_write.py
doepy3/Data/params.csv
doepy3/Data/params.json
doepy3/Test/build_test.py
doepy3/Test/doe_test1.py
doepy3/Test/read_write_test.py
doepy3/Test/system_test.py
doepy3/Test/doepy/__init__.py
doepy3/Test/doepy/build.py
doepy3/Test/doepy/doe_functions.py
doepy3/Test/doepy/params.csv
doepy3/Test/doepy/pydoe_corrected.py
doepy3/Test/doepy/read_write.py
doepy3-0.0.9.dist-info/LICENSE
doepy3-0.0.9.dist-info/METADATA
doepy3-0.0.9.dist-info/WHEEL
doepy3-0.0.9.dist-info/top_level.txt
doepy3-0.0.9.dist-info/RECORD
