Metadata-Version: 2.1
Name: doepy3
Version: 0.0.9
Summary: Design of experiments generator with simple CSV input/output options
Author-email: Tirthajyoti Sarkar <tirthajyoti@gmail.com>, Oliver Breuer <oliver.breuer@fluidon.com>, Adrian Stöckl <adrian.stoeckl@gmail.com>
Project-URL: Homepage, https://github.com/tectas/doepy
Project-URL: Bug Tracker, https://github.com/tectas/doepy/issues
Classifier: Programming Language :: Python :: 3
Classifier: License :: OSI Approved :: MIT License
Classifier: Operating System :: OS Independent
Requires-Python: >=3.7
License-File: LICENSE
Requires-Dist: pyDOE3
Requires-Dist: numpy
Requires-Dist: pandas
Requires-Dist: diversipy
